deviousutils/gcs.py
deviousutils/hf.py
deviousutils/openai.py
deviousutils-0.1.5.dist-info/METADATA
deviousutils-0.1.5.dist-info/WHEEL
deviousutils-0.1.5.dist-info/entry_points.txt
deviousutils-0.1.5.dist-info/top_level.txt
deviousutils-0.1.5.dist-info/RECORD
