Metadata-Version: 2.4
Name: deviousutils
Version: 0.1.5
Requires-Python: >=3.8
Requires-Dist: huggingface_hub
Requires-Dist: pandas
Provides-Extra: dev
Requires-Dist: ruff; extra == "dev"
Requires-Dist: mypy<1.4,>=1.0; extra == "dev"
Requires-Dist: black<24.0,>=23.1; extra == "dev"
Requires-Dist: isort<5.14,>=5.12; extra == "dev"
Requires-Dist: build; extra == "dev"
Requires-Dist: twine>=1.11.0; extra == "dev"
Provides-Extra: all
Requires-Dist: deviousutils[dev]; extra == "all"
